LICENSE.txt
README.md
setup.cfg
setup.py
pyfinviz/__init__.py
pyfinviz/base_url.py
pyfinviz/crypto.py
pyfinviz/groups.py
pyfinviz/insider.py
pyfinviz/news.py
pyfinviz/quote.py
pyfinviz/screener.py
pyfinviz/utils.py
pyfinviz.egg-info/PKG-INFO
pyfinviz.egg-info/SOURCES.txt
pyfinviz.egg-info/dependency_links.txt
pyfinviz.egg-info/requires.txt
pyfinviz.egg-info/top_level.txt