Metadata-Version: 2.1
Name: pyfinviz
Version: 1.1
Summary: Scrape data from finviz.com
Home-page: https://github.com/oscar0812/pyfinviz
Download-URL: https://github.com/oscar0812/pyfinviz/archive/refs/tags/v_1_1.tar.gz
Author: Oscar R. Torres
Author-email: oscar0812torres@gmail.com
License: apache-2.0
Keywords: FINVIZ,STOCKS,SCRAPER,OSCAR RAFAEL TORRES
Classifier: Development Status :: 3 - Alpha
Classifier: Intended Audience :: Developers
Classifier: Topic :: Software Development :: Build Tools
Classifier: License :: OSI Approved :: Apache Software License
Classifier: Programming Language :: Python :: 3
Classifier: Programming Language :: Python :: 3.4
Classifier: Programming Language :: Python :: 3.5
Classifier: Programming Language :: Python :: 3.6
Classifier: Programming Language :: Python :: 3.7
Classifier: Programming Language :: Python :: 3.8
Classifier: Programming Language :: Python :: 3.9
Classifier: Programming Language :: Python :: 3.10
Classifier: Programming Language :: Python :: 3.11
License-File: LICENSE.txt
Requires-Dist: validators
Requires-Dist: beautifulsoup4
Requires-Dist: free-proxy
Requires-Dist: pandas
Requires-Dist: numpy
Requires-Dist: lxml
Requires-Dist: requests
Requires-Dist: python-dotenv
